{
  "id": "you_diagnose_food_allergies_sensitivities",
  "question": "Can you diagnose food allergies and sensitivities using IgG blood tests?",
  "topic": "This addresses the specific misconception about IgG testing accuracy. The podcast mentions high fals",
  "tags": [
    "Food Safety",
    "Medical Testing",
    "Health and Medicine"
  ],
  "sources": [
    {
      "name": "IgG Food Testing Position Statement — American Academy of Allergy, Asthma & Immunology (AAAAI)",
      "url": "https://www.aaaai.org/tools-for-the-public/conditions-library/allergies/igg-food-test",
      "type": "web",
      "tier": 2
    },
    {
      "name": "Food Allergy and Anaphylaxis Guidelines — European Academy of Allergy and Clinical Immunology (EAACI)",
      "url": "https://www.eaaci.org",
      "type": "web",
      "tier": 2
    },
    {
      "name": "Diagnostic accuracy of IgG4 measurements for food allergy: a systematic review — Cochrane Library",
      "url": "https://www.cochranelibrary.com",
      "type": "web",
      "tier": 1
    },
    {
      "name": "Food allergy in under 19s: assessment and diagnosis - Clinical guideline [CG116] — National Institute for Health and Care Excellence (NICE)",
      "url": "https://www.nice.org.uk/guidance/cg116",
      "type": "web",
      "tier": 3
    }
  ],
  "discovery_sources": [
    {
      "type": "podcast_claim",
      "text": "IgG testing has high false positive rate for food reactions - claim made but no specific statistics provided",
      "origin": "Unbiased Science: Food Allergies: A Tough Nut to Crack",
      "url": "https://bleav.com/shows/unbiased-science/?post_type=gp_podcast_episode&p=212",
      "date": "2026-03-04T11:00:00"
    },
    {
      "type": "podcast_topic",
      "text": "IgE-mediated food allergies (immune mechanisms)",
      "origin": "Unbiased Science: Food Allergies: A Tough Nut to Crack",
      "url": "https://bleav.com/shows/unbiased-science/?post_type=gp_podcast_episode&p=212",
      "date": "2026-03-04T11:00:00"
    },
    {
      "type": "podcast_topic",
      "text": "IgG antibody testing for food sensitivities (commercialized testing)",
      "origin": "Unbiased Science: Food Allergies: A Tough Nut to Crack",
      "url": "https://bleav.com/shows/unbiased-science/?post_type=gp_podcast_episode&p=212",
      "date": "2026-03-04T11:00:00"
    },
    {
      "type": "podcast_topic",
      "text": "Oral and sublingual immunotherapy for food allergy treatment",
      "origin": "Unbiased Science: Food Allergies: A Tough Nut to Crack",
      "url": "https://bleav.com/shows/unbiased-science/?post_type=gp_podcast_episode&p=212",
      "date": "2026-03-04T11:00:00"
    },
    {
      "type": "podcast_topic",
      "text": "Celiac disease diagnosis and gluten sensitivity",
      "origin": "Unbiased Science: Food Allergies: A Tough Nut to Crack",
      "url": "https://bleav.com/shows/unbiased-science/?post_type=gp_podcast_episode&p=212",
      "date": "2026-03-04T11:00:00"
    }
  ]
}